financegy/__init__.py
financegy/config.py
financegy/cache/cache_manager.py
financegy/core/parser.py
financegy/core/request_handler.py
financegy/modules/securities.py
financegy/utils/utils.py
financegy-1.5.dist-info/licenses/LICENSE
financegy-1.5.dist-info/METADATA
financegy-1.5.dist-info/WHEEL
financegy-1.5.dist-info/top_level.txt
financegy-1.5.dist-info/RECORD
