Metadata-Version: 2.4
Name: financegy
Version: 1.5
Summary: Unofficial Python library for accessing GSE (Guyana Stock Exchange) financial data
Author-email: Ezra Minty <ezranminty@gmail.com>
License: MIT
Project-URL: Homepage, https://github.com/xbze3/financegy
Project-URL: Issues, https://github.com/xbze3/financegy/issues
License-File: LICENSE
Requires-Dist: requests
Requires-Dist: beautifulsoup4
Requires-Dist: pandas
Requires-Dist: openpyxl
Dynamic: license-file
